<Properties StartupConfiguration="{5F0A04D6-DC2A-4FD8-891C-1D3E25F58B13}|Default">
  <MonoDevelop.Ide.Workbench ActiveDocument="LinqPractice/SubstringTH.cs">
    <Files>
      <File FileName="LinqPractice/Program.cs" Line="1" Column="1" />
      <File FileName="LinqPractice/SubstringTH.cs" Line="2" Column="18" />
    </Files>
  </MonoDevelop.Ide.Workbench>
  <MonoDevelop.Ide.Workspace ActiveConfiguration="Debug|x86" />
  <MonoDevelop.Ide.DebuggingService.Breakpoints>
    <BreakpointStore />
  </MonoDevelop.Ide.DebuggingService.Breakpoints>
  <MonoDevelop.Ide.DebuggingService.PinnedWatches />
  <MonoDevelop.Ide.ItemProperties.LinqPractice PreferredExecutionTarget="MonoDevelop.Default" FirstBuild="True" />
  <MultiItemStartupConfigurations />
</Properties>